eway/utils.py
eway/__init__.py
eway/compat.py
eway/admin.py
eway/apps.py
eway/models.py
eway/south_migrations/0001_initial.py
eway/south_migrations/0004__rename_transaction_classes.py
eway/south_migrations/0002_auto__chg_field_ewaytransaction_txn_ref__chg_field_ewaytransaction_txn.py
eway/south_migrations/__init__.py
eway/south_migrations/0003_auto__del_field_ewaytransaction_txn_ref__del_field_ewaytransaction_txn.py
eway/south_migrations/0005_auto__add_requestlog__add_ewaytransaction.py
eway/south_migrations/0006_copy_to_new_datastructure.py
eway/south_migrations/0008_auto__add_field_transaction_status.py
eway/south_migrations/0007_auto__del_transaction__del_responsecode.py
eway/static/eway/js/rapid.js
eway/templates/eway/dashboard/transaction_list.html
eway/templates/eway/dashboard/transaction_detail.html
eway/management/__init__.py
eway/management/commands/eway_mark_suspicious_transactions.py
eway/management/commands/__init__.py
eway/migrations/0001_initial.py
eway/migrations/0004__rename_transaction_classes.py
eway/migrations/0002_auto__chg_field_ewaytransaction_txn_ref__chg_field_ewaytransaction_txn.py
eway/migrations/__init__.py
eway/migrations/0003_auto__del_field_ewaytransaction_txn_ref__del_field_ewaytransaction_txn.py
eway/migrations/0005_auto__add_requestlog__add_ewaytransaction.py
eway/migrations/0006_copy_to_new_datastructure.py
eway/migrations/0008_auto__add_field_transaction_status.py
eway/migrations/0007_auto__del_transaction__del_responsecode.py
eway/rapid/facade.py
eway/rapid/__init__.py
eway/rapid/forms.py
eway/rapid/compat.py
eway/rapid/gateway.py
eway/rapid/views.py
eway/rapid/mixins.py
eway/rapid/urls.py
eway/dashboard/__init__.py
eway/dashboard/views.py
eway/dashboard/urls.py
django_oscar_eway-0.2.0.dist-info/METADATA
django_oscar_eway-0.2.0.dist-info/metadata.json
django_oscar_eway-0.2.0.dist-info/DESCRIPTION.rst
django_oscar_eway-0.2.0.dist-info/WHEEL
django_oscar_eway-0.2.0.dist-info/top_level.txt
django_oscar_eway-0.2.0.dist-info/RECORD
