Metadata-Version: 2.0
Name: django-oscar-eway
Version: 0.2.0
Summary: eWay payment module for django-oscar (Rapid 3.0)
Home-page: https://github.com/tangentlabs/django-oscar-eway
Author: Sebastian Vetter
Author-email: sebastian.vetter@tangentsnowball.com.au
License: BSD
Keywords: oscar,payment,django,ecommerce,eway,rapid3.0
Platform: UNKNOWN
Classifier: Environment :: Web Environment
Classifier: Framework :: Django
Classifier: Intended Audience :: Developers
Classifier: License :: OSI Approved :: BSD License
Classifier: Operating System :: OS Independent
Classifier: Programming Language :: Python
Requires-Dist: django-oscar (>=0.4)
Requires-Dist: requests (>=1.0)
